idcard/__init__.py
idcard/checker.py
idcard/idcard_test.py
mobile/__init__.py
mobile/checker.py
mobile/mobile_test.py
py_snum_checker-0.1.0.dist-info/METADATA
py_snum_checker-0.1.0.dist-info/WHEEL
py_snum_checker-0.1.0.dist-info/top_level.txt
py_snum_checker-0.1.0.dist-info/RECORD
