Metadata-Version: 2.1
Name: py-snum-checker
Version: 0.1.0
Summary: 社会号码检查器
Home-page: https://gitlab.gugud.com/suyuxp/py-snum-checker.git
Author: Su Yu
Author-email: suyu@zhiyisoft.com
License: MIT
Platform: UNKNOWN
Classifier: License :: OSI Approved :: MIT License
Classifier: Programming Language :: Python
Classifier: Programming Language :: Python :: 3
Classifier: Programming Language :: Python :: 3.6
Classifier: Programming Language :: Python :: Implementation :: CPython
Classifier: Programming Language :: Python :: Implementation :: PyPy
Requires-Python: >=3.8.0
Requires-Dist: httpx
